.travis.yml
CHANGES.txt
COPYRIGHT.txt
LICENSE.txt
MANIFEST.in
README.txt
bootstrap.py
buildout.cfg
setup.py
lib/python3.8/site-packages/grokcore/chameleon/tests/locale/de/LC_MESSAGES/grokcore-chameleon-tests.mo
lib/python3.8/site-packages/grokcore/chameleon/tests/locale/en/LC_MESSAGES/grokcore-chameleon-tests.mo
lib/python3.8/site-packages/pythongettext/tests/test.mo
lib/python3.8/site-packages/pythongettext/tests/test2.mo
lib/python3.8/site-packages/pythongettext/tests/test3.mo
lib/python3.8/site-packages/pythongettext/tests/test6.mo
lib/python3.8/site-packages/pythongettext/tests/test_empty.mo
lib/python3.8/site-packages/pythongettext/tests/test_unicode_bom.mo
lib/python3.8/site-packages/zope/i18n/tests/de-default.mo
lib/python3.8/site-packages/zope/i18n/tests/en-alt.mo
lib/python3.8/site-packages/zope/i18n/tests/en-default.mo
lib/python3.8/site-packages/zope/i18n/tests/pl-default.mo
lib/python3.8/site-packages/zope/i18n/tests/locale/de/LC_MESSAGES/zope-i18n.mo
lib/python3.8/site-packages/zope/i18n/tests/locale/en/LC_MESSAGES/zope-i18n.mo
lib/python3.8/site-packages/zope/i18n/tests/locale2/en/LC_MESSAGES/zope-i18n.mo
lib/python3.8/site-packages/zope/i18n/tests/locale3/en/LC_MESSAGES/zope-i18n.mo
lib64/python3.8/site-packages/grokcore/chameleon/tests/locale/de/LC_MESSAGES/grokcore-chameleon-tests.mo
lib64/python3.8/site-packages/grokcore/chameleon/tests/locale/en/LC_MESSAGES/grokcore-chameleon-tests.mo
lib64/python3.8/site-packages/pythongettext/tests/test.mo
lib64/python3.8/site-packages/pythongettext/tests/test2.mo
lib64/python3.8/site-packages/pythongettext/tests/test3.mo
lib64/python3.8/site-packages/pythongettext/tests/test6.mo
lib64/python3.8/site-packages/pythongettext/tests/test_empty.mo
lib64/python3.8/site-packages/pythongettext/tests/test_unicode_bom.mo
lib64/python3.8/site-packages/zope/i18n/tests/de-default.mo
lib64/python3.8/site-packages/zope/i18n/tests/en-alt.mo
lib64/python3.8/site-packages/zope/i18n/tests/en-default.mo
src/grokui.base.egg-info/PKG-INFO
src/grokui.base.egg-info/SOURCES.txt
src/grokui.base.egg-info/dependency_links.txt
src/grokui.base.egg-info/entry_points.txt
src/grokui.base.egg-info/namespace_packages.txt
src/grokui.base.egg-info/not-zip-safe
src/grokui.base.egg-info/requires.txt
src/grokui.base.egg-info/top_level.txt
