Metadata-Version: 2.1
Name: grokui.base
Version: 0.8.2
Summary: The Grok administration and development UI (base)
Home-page: http://svn.zope.org/grokui.base
Author: Zope Foundation and Contributors
Author-email: grok-dev@zope.org
License: ZPL 2.1
Keywords: zope3 grok grokadmin
Platform: UNKNOWN
Classifier: Development Status :: 3 - Alpha
Classifier: Environment :: Web Environment
Classifier: Intended Audience :: Developers
Classifier: License :: OSI Approved :: Zope Public License
Classifier: Programming Language :: Python
Classifier: Natural Language :: English
Classifier: Operating System :: OS Independent
Classifier: Topic :: Internet :: WWW/HTTP
Classifier: Framework :: Zope :: 3
Provides-Extra: test
